jupyter_ai_litellm/__init__.py
jupyter_ai_litellm/chat_models_rest_api.py
jupyter_ai_litellm/handlers.py
jupyter_ai_litellm/model_list.py
jupyter_ai_litellm/tests/__init__.py
jupyter_ai_litellm/tests/test_handlers.py
jupyter_ai_litellm-0.0.1.data/data/etc/jupyter/jupyter_server_config.d/jupyter_ai_litellm.json
jupyter_ai_litellm-0.0.1.dist-info/METADATA
jupyter_ai_litellm-0.0.1.dist-info/WHEEL
jupyter_ai_litellm-0.0.1.dist-info/licenses/LICENSE
jupyter_ai_litellm-0.0.1.dist-info/RECORD
