Metadata-Version: 2.4
Name: jupyter_ai_litellm
Version: 0.0.1
Summary: A JupyterLab extension that provides LiteLLM model abstraction
Project-URL: Documentation, https://github.com/jupyter-ai-contrib/jupyter-ai-litellm/README.md
Project-URL: Repository, https://github.com/jupyter-ai-contrib/jupyter-ai-litellm
Project-URL: Changelog, https://github.com/jupyter-ai-contrib/jupyter-ai-litellm/CHANGELOG.md
Project-URL: Source, https://github.com/jupyter-ai-contrib/jupyter-ai-litellm/tree/main
Project-URL: Issues, https://github.com/jupyter-ai-contrib/jupyter-ai-litellm/issues/new/choose
Author-email: Project Jupyter <jupyter@googlegroups.com>
License: BSD 3-Clause License
License-File: LICENSE
Classifier: Framework :: Jupyter
Classifier: Framework :: Jupyter :: JupyterLab
Classifier: Framework :: Jupyter :: JupyterLab :: 4
Classifier: Framework :: Jupyter :: JupyterLab :: Extensions
Classifier: Framework :: Jupyter :: JupyterLab :: Extensions :: Prebuilt
Classifier: License :: OSI Approved :: BSD License
Classifier: Programming Language :: Python
Classifier: Programming Language :: Python :: 3
Classifier: Programming Language :: Python :: 3.9
Classifier: Programming Language :: Python :: 3.10
Classifier: Programming Language :: Python :: 3.11
Classifier: Programming Language :: Python :: 3.12
Classifier: Programming Language :: Python :: 3.13
Requires-Python: >=3.9
Requires-Dist: jupyter-server<3,>=2.4.0
Requires-Dist: litellm<2,>=1.73
Provides-Extra: test
Requires-Dist: coverage; extra == 'test'
Requires-Dist: pytest; extra == 'test'
Requires-Dist: pytest-asyncio; extra == 'test'
Requires-Dist: pytest-cov; extra == 'test'
Requires-Dist: pytest-jupyter[server]>=0.6.0; extra == 'test'
